inVAE/__init__.py
inVAE/model/__init__.py
inVAE/model/_abstract_invae.py
inVAE/model/_finvae.py
inVAE/model/_nfinvae.py
inVAE/module/__init__.py
inVAE/module/_finvaemodule.py
inVAE/module/_nfinvaemodule.py
inVAE/utils/__init__.py
inVAE/utils/_helper_functions.py
inVAE/utils/_networks.py
inVAE/utils/_simulation.py
inVAE-0.1.0.dist-info/LICENSE
inVAE-0.1.0.dist-info/METADATA
inVAE-0.1.0.dist-info/WHEEL
inVAE-0.1.0.dist-info/top_level.txt
inVAE-0.1.0.dist-info/RECORD
