Metadata-Version: 2.1
Name: inVAE
Version: 0.1.0
Summary: Package for invariant VAE models on single-cell data
Author-email: Ferdinand Kapl <f.kapl@web.de>, Hananeh Aliee <ha10@sanger.ac.uk>
Project-URL: Homepage, https://github.com/theislab/inVAE
Classifier: Programming Language :: Python :: 3
Classifier: License :: OSI Approved :: MIT License
Classifier: Operating System :: OS Independent
Requires-Python: >=3.7
License-File: LICENSE
Requires-Dist: scanpy
Requires-Dist: torch
Requires-Dist: tensorboard
Requires-Dist: anndata ==0.8.0
